resyst/client/__init__.py
resyst/client/_version.py
resyst/client/acq.py
resyst/client/model_tree.py
resyst/client/program.py
resyst/client/system.py
resyst/client/model/gui.py
resyst/client/model/gui_app.py
resyst/client/model/gui_base.py
resyst/libdeep/__init__.py
resyst/libdeep/clibdeep.py
resyst/libdeep/dconfig.py
resyst/libdeep/deepobject.py
resyst/libdeep/device.py
resyst/libdeep/dframe.py
resyst/libdeep/dparser.py
resyst/libdeep/libdeep.so
resyst/libdeep/unused_deeparray.py
resyst/libdeep/unused_deepasync.py
resyst/libdeep/unused_deepbuffer.py
resyst/libdeep/unused_deeplog.py
resyst_client-0.18.1.dist-info/licenses/LICENSE
resyst_client-0.18.1.dist-info/METADATA
resyst_client-0.18.1.dist-info/WHEEL
resyst_client-0.18.1.dist-info/entry_points.txt
resyst_client-0.18.1.dist-info/top_level.txt
resyst_client-0.18.1.dist-info/RECORD
