Metadata-Version: 2.4
Name: resyst-client
Version: 0.18.1
Summary: Hybrid DAnCE Client for communicating with a RESYST Hybrid DAnCE Server.
Author-email: Bruno Martin <bruno.martin@esrf.fr>, Pablo Fajardo <fajardo@esrf.fr>
Maintainer-email: Bruno Martin <bruno.martin@esrf.fr>
License-Expression: MIT
Project-URL: Homepage, https://gitlab.esrf.fr/deg/devel/resyst/client
Project-URL: Issues, https://gitlab.esrf.fr/deg/devel/resyst/client/-/issues
Classifier: Programming Language :: Python :: 3
Classifier: Programming Language :: Python :: 3.9
Classifier: Programming Language :: Python :: 3.10
Classifier: Programming Language :: Python :: 3.11
Classifier: Programming Language :: Python :: 3.12
Classifier: Programming Language :: Python :: 3.13
Classifier: Operating System :: POSIX :: Linux
Requires-Python: <3.14,>=3.9
License-File: LICENSE
Requires-Dist: numpy<2.0,>=1.21.1
Requires-Dist: packaging
Provides-Extra: test
Requires-Dist: pytest==8.3.5; extra == "test"
Requires-Dist: dotenv; extra == "test"
Requires-Dist: pytest-cov==7.0.0; extra == "test"
Requires-Dist: gevent==25.9.1; extra == "test"
Provides-Extra: doc
Requires-Dist: sphinx==7.1.2; extra == "doc"
Requires-Dist: sphinx-rtd-theme==1.3.0rc1; extra == "doc"
Requires-Dist: sphinxcontrib-kroki==1.3.0; extra == "doc"
Requires-Dist: sphinx-multiversion==0.2.4; extra == "doc"
Requires-Dist: setuptools; extra == "doc"
Provides-Extra: build
Requires-Dist: build; extra == "build"
Requires-Dist: twine; extra == "build"
Provides-Extra: all
Requires-Dist: resyst-client[build,doc,test]; extra == "all"
Dynamic: license-file
